aad/__init__.py
aad/main.py
aad/fastapi/__init__.py
aad/fastapi/dependency.py
aad/util/__init__.py
aad/util/cyrpto.py
aad/util/jwks.py
aad/util/meta.py
aad/util/req.py
aad-0.1.5.dist-info/METADATA
aad-0.1.5.dist-info/WHEEL
aad-0.1.5.dist-info/top_level.txt
aad-0.1.5.dist-info/RECORD
