Metadata-Version: 2.1
Name: aad
Version: 0.1.5
Summary: Async Python SDK for validating Azure AD B2C access tokens
Author-email: Marcel Claramunt <marcel@moveread.com>
Project-URL: home, https://github.com/moveread/azure-sdks/tree/main/sdks/aad-b2c
Project-URL: repo, https://github.com/moveread/azure-sdks
Requires-Python: >=3.10
Requires-Dist: aiohttp
Requires-Dist: pydantic
Requires-Dist: pyjwt
Provides-Extra: fastapi
Requires-Dist: fastapi ; extra == 'fastapi'
